[
  {
    "graph_type": "Gnp",
    "n": 1024,
    "reachable_n": 1023,
    "m": 16198,
    "avg_deg": 15.818359375,
    "blocksize": 65536,
    "e_b": 1,
    "seed": 19,
    "distribution": "Uniform",
    "barabasi_m": 0,
    "io_dijkstra_simplified": 1024,
    "io_bellman_full": 14,
    "io_dj_to_bf_best_switch": 14.0,
    "io_hybrid_multi": 13,
    "io_cost_landmark": 467,
    "io_best_switches_overall": 13.0,
    "io_Ip": -1
  },
  {
    "graph_type": "Gnp",
    "n": 1448,
    "reachable_n": 1447,
    "m": 22990,
    "avg_deg": 15.87707182320442,
    "blocksize": 65536,
    "e_b": 1,
    "seed": 19,
    "distribution": "Uniform",
    "barabasi_m": 0,
    "io_dijkstra_simplified": 1448,
    "io_bellman_full": 14,
    "io_dj_to_bf_best_switch": 14.0,
    "io_hybrid_multi": 13,
    "io_cost_landmark": 677,
    "io_best_switches_overall": 13.0,
    "io_Ip": -1
  },
  {
    "graph_type": "Gnp",
    "n": 2048,
    "reachable_n": 2047,
    "m": 32506,
    "avg_deg": 15.8720703125,
    "blocksize": 65536,
    "e_b": 1,
    "seed": 19,
    "distribution": "Uniform",
    "barabasi_m": 0,
    "io_dijkstra_simplified": 2048,
    "io_bellman_full": 15,
    "io_dj_to_bf_best_switch": 15.0,
    "io_hybrid_multi": 14,
    "io_cost_landmark": 801,
    "io_best_switches_overall": 14.0,
    "io_Ip": -1
  },
  {
    "graph_type": "Gnp",
    "n": 2896,
    "reachable_n": 2895,
    "m": 46321,
    "avg_deg": 15.994820441988951,
    "blocksize": 65536,
    "e_b": 1,
    "seed": 19,
    "distribution": "Uniform",
    "barabasi_m": 0,
    "io_dijkstra_simplified": 2896,
    "io_bellman_full": 16,
    "io_dj_to_bf_best_switch": 16.0,
    "io_hybrid_multi": 15,
    "io_cost_landmark": 804,
    "io_best_switches_overall": 15.0,
    "io_Ip": -1
  },
  {
    "graph_type": "Gnp",
    "n": 4096,
    "reachable_n": 4095,
    "m": 65479,
    "avg_deg": 15.986083984375,
    "blocksize": 65536,
    "e_b": 1,
    "seed": 19,
    "distribution": "Uniform",
    "barabasi_m": 0,
    "io_dijkstra_simplified": 4096,
    "io_bellman_full": 19,
    "io_dj_to_bf_best_switch": 19.0,
    "io_hybrid_multi": 18,
    "io_cost_landmark": 1057,
    "io_best_switches_overall": 18.0,
    "io_Ip": -1
  },
  {
    "graph_type": "Gnp",
    "n": 5793,
    "reachable_n": 5792,
    "m": 92716,
    "avg_deg": 16.0048334196444,
    "blocksize": 65536,
    "e_b": 2,
    "seed": 19,
    "distribution": "Uniform",
    "barabasi_m": 0,
    "io_dijkstra_simplified": 5793,
    "io_bellman_full": 36,
    "io_dj_to_bf_best_switch": 35.0,
    "io_hybrid_multi": 33,
    "io_cost_landmark": 1603,
    "io_best_switches_overall": 33.0,
    "io_Ip": -1
  },
  {
    "graph_type": "Gnp",
    "n": 8192,
    "reachable_n": 8191,
    "m": 131049,
    "avg_deg": 15.9971923828125,
    "blocksize": 65536,
    "e_b": 2,
    "seed": 19,
    "distribution": "Uniform",
    "barabasi_m": 0,
    "io_dijkstra_simplified": 8192,
    "io_bellman_full": 40,
    "io_dj_to_bf_best_switch": 37.0,
    "io_hybrid_multi": 37,
    "io_cost_landmark": 1891,
    "io_best_switches_overall": 37.0,
    "io_Ip": -1
  },
  {
    "graph_type": "Gnp",
    "n": 11585,
    "reachable_n": 11584,
    "m": 185421,
    "avg_deg": 16.005265429434615,
    "blocksize": 65536,
    "e_b": 3,
    "seed": 19,
    "distribution": "Uniform",
    "barabasi_m": 0,
    "io_dijkstra_simplified": 11585,
    "io_bellman_full": 66,
    "io_dj_to_bf_best_switch": 61.0,
    "io_hybrid_multi": 60,
    "io_cost_landmark": 3018,
    "io_best_switches_overall": 58.0,
    "io_Ip": -1
  },
  {
    "graph_type": "Gnp",
    "n": 16384,
    "reachable_n": 16383,
    "m": 262495,
    "avg_deg": 16.02142333984375,
    "blocksize": 65536,
    "e_b": 5,
    "seed": 19,
    "distribution": "Uniform",
    "barabasi_m": 0,
    "io_dijkstra_simplified": 16384,
    "io_bellman_full": 105,
    "io_dj_to_bf_best_switch": 97.0,
    "io_hybrid_multi": 95,
    "io_cost_landmark": 4903,
    "io_best_switches_overall": 85.0,
    "io_Ip": -1
  },
  {
    "graph_type": "Gnp",
    "n": 23170,
    "reachable_n": 23169,
    "m": 371238,
    "avg_deg": 16.022356495468276,
    "blocksize": 65536,
    "e_b": 6,
    "seed": 19,
    "distribution": "Uniform",
    "barabasi_m": 0,
    "io_dijkstra_simplified": 23170,
    "io_bellman_full": 138,
    "io_dj_to_bf_best_switch": 129.0,
    "io_hybrid_multi": 127,
    "io_cost_landmark": 5361,
    "io_best_switches_overall": 114.0,
    "io_Ip": -1
  },
  {
    "graph_type": "Gnp",
    "n": 32768,
    "reachable_n": 32767,
    "m": 525281,
    "avg_deg": 16.030303955078125,
    "blocksize": 65536,
    "e_b": 9,
    "seed": 19,
    "distribution": "Uniform",
    "barabasi_m": 0,
    "io_dijkstra_simplified": 32768,
    "io_bellman_full": 216,
    "io_dj_to_bf_best_switch": 174.0,
    "io_hybrid_multi": 193,
    "io_cost_landmark": 8899,
    "io_best_switches_overall": 175.0,
    "io_Ip": -1
  },
  {
    "graph_type": "Gnp",
    "n": 46341,
    "reachable_n": 46340,
    "m": 743312,
    "avg_deg": 16.040050926825057,
    "blocksize": 65536,
    "e_b": 12,
    "seed": 19,
    "distribution": "Uniform",
    "barabasi_m": 0,
    "io_dijkstra_simplified": 46341,
    "io_bellman_full": 288,
    "io_dj_to_bf_best_switch": 246.0,
    "io_hybrid_multi": 263,
    "io_cost_landmark": 13286,
    "io_best_switches_overall": 242.0,
    "io_Ip": -1
  },
  {
    "graph_type": "Gnp",
    "n": 65536,
    "reachable_n": 65535,
    "m": 1049914,
    "avg_deg": 16.020416259765625,
    "blocksize": 65536,
    "e_b": 17,
    "seed": 19,
    "distribution": "Uniform",
    "barabasi_m": 0,
    "io_dijkstra_simplified": 65536,
    "io_bellman_full": 425,
    "io_dj_to_bf_best_switch": 362.0,
    "io_hybrid_multi": 367,
    "io_cost_landmark": 14357,
    "io_best_switches_overall": 327.0,
    "io_Ip": -1
  },
  {
    "graph_type": "Gnp",
    "n": 92682,
    "reachable_n": 92681,
    "m": 1483778,
    "avg_deg": 16.009343777648304,
    "blocksize": 65536,
    "e_b": 23,
    "seed": 19,
    "distribution": "Uniform",
    "barabasi_m": 0,
    "io_dijkstra_simplified": 92682,
    "io_bellman_full": 598,
    "io_dj_to_bf_best_switch": 514.0,
    "io_hybrid_multi": 515,
    "io_cost_landmark": 20113,
    "io_best_switches_overall": 469.0,
    "io_Ip": -1
  },
  {
    "graph_type": "Gnp",
    "n": 131072,
    "reachable_n": 131071,
    "m": 2097906,
    "avg_deg": 16.005752563476562,
    "blocksize": 65536,
    "e_b": 33,
    "seed": 19,
    "distribution": "Uniform",
    "barabasi_m": 0,
    "io_dijkstra_simplified": 131072,
    "io_bellman_full": 825,
    "io_dj_to_bf_best_switch": 698.0,
    "io_hybrid_multi": 739,
    "io_cost_landmark": 48917,
    "io_best_switches_overall": 664.0,
    "io_Ip": -1
  },
  {
    "graph_type": "Gnp",
    "n": 185364,
    "reachable_n": 185363,
    "m": 2965773,
    "avg_deg": 15.999724865669709,
    "blocksize": 65536,
    "e_b": 46,
    "seed": 19,
    "distribution": "Uniform",
    "barabasi_m": 0,
    "io_dijkstra_simplified": 185364,
    "io_bellman_full": 1472,
    "io_dj_to_bf_best_switch": 1145.0,
    "io_hybrid_multi": 1232,
    "io_cost_landmark": 30071,
    "io_best_switches_overall": 1061.0,
    "io_Ip": -1
  },
  {
    "graph_type": "Gnp",
    "n": 262144,
    "reachable_n": 262143,
    "m": 4193833,
    "avg_deg": 15.99820327758789,
    "blocksize": 65536,
    "e_b": 64,
    "seed": 19,
    "distribution": "Uniform",
    "barabasi_m": 0,
    "io_dijkstra_simplified": 262144,
    "io_bellman_full": 1856,
    "io_dj_to_bf_best_switch": 1483.0,
    "io_hybrid_multi": 1566,
    "io_cost_landmark": 47823,
    "io_best_switches_overall": 1493.0,
    "io_Ip": -1
  },
  {
    "graph_type": "Gnp",
    "n": 370728,
    "reachable_n": 370727,
    "m": 5930223,
    "avg_deg": 15.996156211562116,
    "blocksize": 65536,
    "e_b": 91,
    "seed": 19,
    "distribution": "Uniform",
    "barabasi_m": 0,
    "io_dijkstra_simplified": 370728,
    "io_bellman_full": 2821,
    "io_dj_to_bf_best_switch": 2086.0,
    "io_hybrid_multi": 2177,
    "io_cost_landmark": 86716,
    "io_best_switches_overall": 2109.0,
    "io_Ip": -1
  },
  {
    "graph_type": "Gnp",
    "n": 524288,
    "reachable_n": 524287,
    "m": 8386513,
    "avg_deg": 15.996004104614258,
    "blocksize": 65536,
    "e_b": 128,
    "seed": 19,
    "distribution": "Uniform",
    "barabasi_m": 0,
    "io_dijkstra_simplified": 524288,
    "io_bellman_full": 3712,
    "io_dj_to_bf_best_switch": 3083.0,
    "io_hybrid_multi": 2897,
    "io_cost_landmark": 159554,
    "io_best_switches_overall": 2914.0,
    "io_Ip": -1
  },
  {
    "graph_type": "Gnp",
    "n": 741455,
    "reachable_n": 741454,
    "m": 11863462,
    "avg_deg": 16.000245463312,
    "blocksize": 65536,
    "e_b": 182,
    "seed": 19,
    "distribution": "Uniform",
    "barabasi_m": 0,
    "io_dijkstra_simplified": 741455,
    "io_bellman_full": 5824,
    "io_dj_to_bf_best_switch": 4402.0,
    "io_hybrid_multi": 4328,
    "io_cost_landmark": 182186,
    "io_best_switches_overall": 4085.0,
    "io_Ip": -1
  },
  {
    "graph_type": "Gnp",
    "n": 1048576,
    "reachable_n": 1048575,
    "m": 16775641,
    "avg_deg": 15.99849796295166,
    "blocksize": 65536,
    "e_b": 256,
    "seed": 19,
    "distribution": "Uniform",
    "barabasi_m": 0,
    "io_dijkstra_simplified": 1048576,
    "io_bellman_full": 8960,
    "io_dj_to_bf_best_switch": 6298.0,
    "io_hybrid_multi": 6220,
    "io_cost_landmark": 234015,
    "io_best_switches_overall": 6262.0,
    "io_Ip": -1
  },
  {
    "graph_type": "Gnp",
    "n": 1482910,
    "reachable_n": 1482909,
    "m": 23724968,
    "avg_deg": 15.998926435184872,
    "blocksize": 65536,
    "e_b": 363,
    "seed": 19,
    "distribution": "Uniform",
    "barabasi_m": 0,
    "io_dijkstra_simplified": 1482910,
    "io_bellman_full": 12705,
    "io_dj_to_bf_best_switch": 9051.0,
    "io_hybrid_multi": 9070,
    "io_cost_landmark": 380837,
    "io_best_switches_overall": 9740.0,
    "io_Ip": -1
  },
  {
    "graph_type": "Gnp",
    "n": 2097152,
    "reachable_n": 2097151,
    "m": 33556004,
    "avg_deg": 16.000749588012695,
    "blocksize": 65536,
    "e_b": 513,
    "seed": 19,
    "distribution": "Uniform",
    "barabasi_m": 0,
    "io_dijkstra_simplified": 2097152,
    "io_bellman_full": 20007,
    "io_dj_to_bf_best_switch": 12599.0,
    "io_hybrid_multi": 13380,
    "io_cost_landmark": 227384,
    "io_best_switches_overall": 13197.0,
    "io_Ip": -1
  },
  {
    "graph_type": "Gnp",
    "n": 2965821,
    "reachable_n": 2965820,
    "m": 47451449,
    "avg_deg": 15.99943118617071,
    "blocksize": 65536,
    "e_b": 725,
    "seed": 19,
    "distribution": "Uniform",
    "barabasi_m": 0,
    "io_dijkstra_simplified": 2965821,
    "io_bellman_full": 25375,
    "io_dj_to_bf_best_switch": 19099.0,
    "io_hybrid_multi": 17289,
    "io_cost_landmark": 689626,
    "io_best_switches_overall": 17691.0,
    "io_Ip": -1
  },
  {
    "graph_type": "Gnp",
    "n": 4194304,
    "reachable_n": 4194303,
    "m": 67110259,
    "avg_deg": 16.000332593917847,
    "blocksize": 65536,
    "e_b": 1025,
    "seed": 19,
    "distribution": "Uniform",
    "barabasi_m": 0,
    "io_dijkstra_simplified": 4194304,
    "io_bellman_full": 34850,
    "io_dj_to_bf_best_switch": 25622.0,
    "io_hybrid_multi": 25062,
    "io_cost_landmark": 1203344,
    "io_best_switches_overall": 24893.0,
    "io_Ip": -1
  },
  {
    "summary": "asymptotic_stats",
    "alpha_r2": {
      "io_dijkstra_simplified": [
        0.9999290172938894,
        0.99999999566285
      ],
      "io_bellman_full": [
        1.023628437149609,
        0.9925382799896773
      ],
      "io_dj_to_bf_best_switch": [
        0.9751024619752249,
        0.9926550351394913
      ],
      "io_hybrid_multi": [
        0.9821912093996356,
        0.9936175714788809
      ],
      "io_cost_landmark": [
        0.9325972110819587,
        0.9885265429597401
      ],
      "io_best_switches_overall": [
        0.9832373519521558,
        0.9927053525697398
      ]
    }
  }
]