[
  {
    "graph_type": "Geometric",
    "n": 1024,
    "reachable_n": 1023,
    "m": 15644,
    "avg_deg": 15.27734375,
    "blocksize": 4096,
    "e_b": 4,
    "seed": 19,
    "distribution": "Exp",
    "barabasi_m": 0,
    "io_dijkstra_simplified": 1024,
    "io_bellman_full": 144,
    "io_dj_to_bf_best_switch": 137.0,
    "io_hybrid_multi": 136,
    "io_cost_landmark": 614,
    "io_best_switches_overall": 128.0,
    "io_Ip": -1
  },
  {
    "graph_type": "Geometric",
    "n": 1448,
    "reachable_n": 1447,
    "m": 22028,
    "avg_deg": 15.212707182320441,
    "blocksize": 4096,
    "e_b": 6,
    "seed": 19,
    "distribution": "Exp",
    "barabasi_m": 0,
    "io_dijkstra_simplified": 1448,
    "io_bellman_full": 312,
    "io_dj_to_bf_best_switch": 300.0,
    "io_hybrid_multi": 297,
    "io_cost_landmark": 1162,
    "io_best_switches_overall": 232.0,
    "io_Ip": -1
  },
  {
    "graph_type": "Geometric",
    "n": 2048,
    "reachable_n": 2047,
    "m": 31404,
    "avg_deg": 15.333984375,
    "blocksize": 4096,
    "e_b": 8,
    "seed": 19,
    "distribution": "Exp",
    "barabasi_m": 0,
    "io_dijkstra_simplified": 2048,
    "io_bellman_full": 472,
    "io_dj_to_bf_best_switch": 436.0,
    "io_hybrid_multi": 454,
    "io_cost_landmark": 1587,
    "io_best_switches_overall": 423.0,
    "io_Ip": -1
  },
  {
    "graph_type": "Geometric",
    "n": 2896,
    "reachable_n": 2895,
    "m": 44524,
    "avg_deg": 15.374309392265193,
    "blocksize": 4096,
    "e_b": 11,
    "seed": 19,
    "distribution": "Exp",
    "barabasi_m": 0,
    "io_dijkstra_simplified": 2896,
    "io_bellman_full": 594,
    "io_dj_to_bf_best_switch": 550.0,
    "io_hybrid_multi": 571,
    "io_cost_landmark": 1914,
    "io_best_switches_overall": 548.0,
    "io_Ip": -1
  },
  {
    "graph_type": "Geometric",
    "n": 4096,
    "reachable_n": 4095,
    "m": 63662,
    "avg_deg": 15.54248046875,
    "blocksize": 4096,
    "e_b": 16,
    "seed": 19,
    "distribution": "Exp",
    "barabasi_m": 0,
    "io_dijkstra_simplified": 4096,
    "io_bellman_full": 1056,
    "io_dj_to_bf_best_switch": 1002.0,
    "io_hybrid_multi": 1003,
    "io_cost_landmark": 2974,
    "io_best_switches_overall": 919.0,
    "io_Ip": -1
  },
  {
    "graph_type": "Geometric",
    "n": 5793,
    "reachable_n": 5792,
    "m": 90502,
    "avg_deg": 15.622648023476609,
    "blocksize": 4096,
    "e_b": 23,
    "seed": 19,
    "distribution": "Exp",
    "barabasi_m": 0,
    "io_dijkstra_simplified": 5793,
    "io_bellman_full": 2116,
    "io_dj_to_bf_best_switch": 1940.0,
    "io_hybrid_multi": 2024,
    "io_cost_landmark": 4935,
    "io_best_switches_overall": 1568.0,
    "io_Ip": -1
  },
  {
    "graph_type": "Geometric",
    "n": 8192,
    "reachable_n": 8191,
    "m": 129124,
    "avg_deg": 15.76220703125,
    "blocksize": 4096,
    "e_b": 32,
    "seed": 19,
    "distribution": "Exp",
    "barabasi_m": 0,
    "io_dijkstra_simplified": 8192,
    "io_bellman_full": 3584,
    "io_dj_to_bf_best_switch": 3371.0,
    "io_hybrid_multi": 3294,
    "io_cost_landmark": 7996,
    "io_best_switches_overall": 2494.0,
    "io_Ip": -1
  },
  {
    "graph_type": "Geometric",
    "n": 11585,
    "reachable_n": 11584,
    "m": 182322,
    "avg_deg": 15.737764350453173,
    "blocksize": 4096,
    "e_b": 45,
    "seed": 19,
    "distribution": "Exp",
    "barabasi_m": 0,
    "io_dijkstra_simplified": 11585,
    "io_bellman_full": 5490,
    "io_dj_to_bf_best_switch": 5241.0,
    "io_hybrid_multi": 4966,
    "io_cost_landmark": 10584,
    "io_best_switches_overall": 3947.0,
    "io_Ip": -1
  },
  {
    "graph_type": "Geometric",
    "n": 16384,
    "reachable_n": 16383,
    "m": 258060,
    "avg_deg": 15.750732421875,
    "blocksize": 4096,
    "e_b": 64,
    "seed": 19,
    "distribution": "Exp",
    "barabasi_m": 0,
    "io_dijkstra_simplified": 16384,
    "io_bellman_full": 7616,
    "io_dj_to_bf_best_switch": 6765.0,
    "io_hybrid_multi": 6868,
    "io_cost_landmark": 14911,
    "io_best_switches_overall": 5551.0,
    "io_Ip": -1
  },
  {
    "graph_type": "Geometric",
    "n": 23170,
    "reachable_n": 23169,
    "m": 366038,
    "avg_deg": 15.797928355632283,
    "blocksize": 4096,
    "e_b": 90,
    "seed": 19,
    "distribution": "Exp",
    "barabasi_m": 0,
    "io_dijkstra_simplified": 23170,
    "io_bellman_full": 15660,
    "io_dj_to_bf_best_switch": 13771.0,
    "io_hybrid_multi": 14428,
    "io_cost_landmark": 28464,
    "io_best_switches_overall": 10471.0,
    "io_Ip": -1
  },
  {
    "graph_type": "Geometric",
    "n": 32768,
    "reachable_n": 32766,
    "m": 521296,
    "avg_deg": 15.90869140625,
    "blocksize": 4096,
    "e_b": 128,
    "seed": 19,
    "distribution": "Exp",
    "barabasi_m": 0,
    "io_dijkstra_simplified": 32767,
    "io_bellman_full": 25472,
    "io_dj_to_bf_best_switch": 23607.0,
    "io_hybrid_multi": 22537,
    "io_cost_landmark": 39071,
    "io_best_switches_overall": 14295.0,
    "io_Ip": -1
  },
  {
    "graph_type": "Geometric",
    "n": 46341,
    "reachable_n": 46340,
    "m": 737898,
    "avg_deg": 15.923221337476532,
    "blocksize": 4096,
    "e_b": 181,
    "seed": 19,
    "distribution": "Exp",
    "barabasi_m": 0,
    "io_dijkstra_simplified": 46341,
    "io_bellman_full": 45069,
    "io_dj_to_bf_best_switch": 41953.0,
    "io_hybrid_multi": 42379,
    "io_cost_landmark": 65877,
    "io_best_switches_overall": 22485.0,
    "io_Ip": -1
  },
  {
    "graph_type": "Geometric",
    "n": 65536,
    "reachable_n": 65535,
    "m": 1042892,
    "avg_deg": 15.91326904296875,
    "blocksize": 4096,
    "e_b": 255,
    "seed": 19,
    "distribution": "Exp",
    "barabasi_m": 0,
    "io_dijkstra_simplified": 65536,
    "io_bellman_full": 83640,
    "io_dj_to_bf_best_switch": 65536.0,
    "io_hybrid_multi": 77834,
    "io_cost_landmark": 119071,
    "io_best_switches_overall": 35588.0,
    "io_Ip": -1
  },
  {
    "graph_type": "Geometric",
    "n": 92682,
    "reachable_n": 92680,
    "m": 1473860,
    "avg_deg": 15.902332707537601,
    "blocksize": 4096,
    "e_b": 360,
    "seed": 19,
    "distribution": "Exp",
    "barabasi_m": 0,
    "io_dijkstra_simplified": 92681,
    "io_bellman_full": 115200,
    "io_dj_to_bf_best_switch": 92681.0,
    "io_hybrid_multi": 106255,
    "io_cost_landmark": 165232,
    "io_best_switches_overall": 51758.0,
    "io_Ip": -1
  },
  {
    "graph_type": "Geometric",
    "n": 131072,
    "reachable_n": 131071,
    "m": 2083908,
    "avg_deg": 15.898956298828125,
    "blocksize": 4096,
    "e_b": 509,
    "seed": 19,
    "distribution": "Exp",
    "barabasi_m": 0,
    "io_dijkstra_simplified": 131072,
    "io_bellman_full": 175605,
    "io_dj_to_bf_best_switch": 131072.0,
    "io_hybrid_multi": 151171,
    "io_cost_landmark": 234251,
    "io_best_switches_overall": 73200.0,
    "io_Ip": -1
  },
  {
    "graph_type": "Geometric",
    "n": 185364,
    "reachable_n": 185362,
    "m": 2947410,
    "avg_deg": 15.900660322392698,
    "blocksize": 4096,
    "e_b": 720,
    "seed": 19,
    "distribution": "Exp",
    "barabasi_m": 0,
    "io_dijkstra_simplified": 185363,
    "io_bellman_full": 277200,
    "io_dj_to_bf_best_switch": 185363.0,
    "io_hybrid_multi": 235082,
    "io_cost_landmark": 359255,
    "io_best_switches_overall": 103657.0,
    "io_Ip": -1
  },
  {
    "graph_type": "Geometric",
    "n": 262144,
    "reachable_n": 262142,
    "m": 4173378,
    "avg_deg": 15.920173645019531,
    "blocksize": 4096,
    "e_b": 1019,
    "seed": 19,
    "distribution": "Exp",
    "barabasi_m": 0,
    "io_dijkstra_simplified": 262143,
    "io_bellman_full": 475873,
    "io_dj_to_bf_best_switch": 262143.0,
    "io_hybrid_multi": 399938,
    "io_cost_landmark": 596266,
    "io_best_switches_overall": 146286.0,
    "io_Ip": -1
  },
  {
    "graph_type": "Geometric",
    "n": 370728,
    "reachable_n": 370727,
    "m": 5905992,
    "avg_deg": 15.930795623745711,
    "blocksize": 4096,
    "e_b": 1442,
    "seed": 19,
    "distribution": "Exp",
    "barabasi_m": 0,
    "io_dijkstra_simplified": 370728,
    "io_bellman_full": 1041124,
    "io_dj_to_bf_best_switch": 370728.0,
    "io_hybrid_multi": 893740,
    "io_cost_landmark": 1230898,
    "io_best_switches_overall": 206652.0,
    "io_Ip": -1
  },
  {
    "graph_type": "Geometric",
    "n": 524288,
    "reachable_n": 524287,
    "m": 8361398,
    "avg_deg": 15.948101043701172,
    "blocksize": 4096,
    "e_b": 2042,
    "seed": 19,
    "distribution": "Exp",
    "barabasi_m": 0,
    "io_dijkstra_simplified": 524288,
    "io_bellman_full": 1641768,
    "io_dj_to_bf_best_switch": 524288.0,
    "io_hybrid_multi": 1389126,
    "io_cost_landmark": 1905902,
    "io_best_switches_overall": 292163.0,
    "io_Ip": -1
  },
  {
    "graph_type": "Geometric",
    "n": 741455,
    "reachable_n": 741453,
    "m": 11833984,
    "avg_deg": 15.960488498964873,
    "blocksize": 4096,
    "e_b": 2890,
    "seed": 19,
    "distribution": "Exp",
    "barabasi_m": 0,
    "io_dijkstra_simplified": 741454,
    "io_bellman_full": 3080740,
    "io_dj_to_bf_best_switch": 741454.0,
    "io_hybrid_multi": 2065227,
    "io_cost_landmark": 3460844,
    "io_best_switches_overall": 413516.0,
    "io_Ip": -1
  },
  {
    "graph_type": "Geometric",
    "n": 1048576,
    "reachable_n": 1048574,
    "m": 16738194,
    "avg_deg": 15.962785720825195,
    "blocksize": 4096,
    "e_b": 4087,
    "seed": 19,
    "distribution": "Exp",
    "barabasi_m": 0,
    "io_dijkstra_simplified": 1048575,
    "io_bellman_full": 5002488,
    "io_dj_to_bf_best_switch": 1048575.0,
    "io_hybrid_multi": 3165539,
    "io_cost_landmark": 5563657,
    "io_best_switches_overall": 584606.0,
    "io_Ip": -1
  },
  {
    "graph_type": "Geometric",
    "n": 1482910,
    "reachable_n": 1482909,
    "m": 23686480,
    "avg_deg": 15.972972061689516,
    "blocksize": 4096,
    "e_b": 5783,
    "seed": 19,
    "distribution": "Exp",
    "barabasi_m": 0,
    "io_dijkstra_simplified": 1482910,
    "io_bellman_full": 7159354,
    "io_dj_to_bf_best_switch": 1482910.0,
    "io_hybrid_multi": 5109542,
    "io_cost_landmark": 7837740,
    "io_best_switches_overall": 826412.0,
    "io_Ip": -1
  },
  {
    "graph_type": "Geometric",
    "n": 2097152,
    "reachable_n": 2097150,
    "m": 33503496,
    "avg_deg": 15.975711822509766,
    "blocksize": 4096,
    "e_b": 8180,
    "seed": 19,
    "distribution": "Exp",
    "barabasi_m": 0,
    "io_dijkstra_simplified": 2097151,
    "io_bellman_full": 14756720,
    "io_dj_to_bf_best_switch": 2097151.0,
    "io_hybrid_multi": 6333871,
    "io_cost_landmark": 15856344,
    "io_best_switches_overall": 1170139.0,
    "io_Ip": -1
  },
  {
    "graph_type": "Geometric",
    "n": 2965821,
    "reachable_n": 2965819,
    "m": 47390420,
    "avg_deg": 15.97885374741092,
    "blocksize": 4096,
    "e_b": 11570,
    "seed": 19,
    "distribution": "Exp",
    "barabasi_m": 0,
    "io_dijkstra_simplified": 2965820,
    "io_bellman_full": 20745010,
    "io_dj_to_bf_best_switch": 2965820.0,
    "io_hybrid_multi": 2965820,
    "io_cost_landmark": 22222703,
    "io_best_switches_overall": 1653907.0,
    "io_Ip": -1
  },
  {
    "graph_type": "Geometric",
    "n": 4194304,
    "reachable_n": 4194303,
    "m": 67033094,
    "avg_deg": 15.981935024261475,
    "blocksize": 4096,
    "e_b": 16366,
    "seed": 19,
    "distribution": "Exp",
    "barabasi_m": 0,
    "io_dijkstra_simplified": 4194304,
    "io_bellman_full": 28296814,
    "io_dj_to_bf_best_switch": 4194304.0,
    "io_hybrid_multi": 14188617,
    "io_cost_landmark": 30207026,
    "io_best_switches_overall": 2340065.0,
    "io_Ip": -1
  },
  {
    "summary": "asymptotic_stats",
    "alpha_r2": {
      "io_dijkstra_simplified": [
        0.9999290173270615,
        0.9999999956628465
      ],
      "io_bellman_full": [
        1.4828181899123785,
        0.9988743167029668
      ],
      "io_dj_to_bf_best_switch": [
        1.2350624489991529,
        0.990663529586475
      ],
      "io_hybrid_multi": [
        1.3800608313792504,
        0.9915077302401379
      ],
      "io_cost_landmark": [
        1.3197862410414503,
        0.9969834776173487
      ],
      "io_best_switches_overall": [
        1.1620136709830404,
        0.9944628337327992
      ]
    }
  }
]